zulip_emoji_mapping/__init__.py
zulip_emoji_mapping/__main__.py
zulip_emoji_mapping/emoji_names.py
zulip_emoji_mapping-1.0.1.dist-info/LICENSE
zulip_emoji_mapping-1.0.1.dist-info/METADATA
zulip_emoji_mapping-1.0.1.dist-info/WHEEL
zulip_emoji_mapping-1.0.1.dist-info/RECORD
