Metadata-Version: 2.1
Name: zulip-emoji-mapping
Version: 1.0.1
Summary: A Zulip emoji name mapping
License: Apache-2.0
Author: GearKite
Author-email: emgh@em.id.lv
Requires-Python: >=3.8,<4.0
Classifier: License :: OSI Approved :: Apache Software License
Classifier: Programming Language :: Python :: 3
Classifier: Programming Language :: Python :: 3.8
Classifier: Programming Language :: Python :: 3.9
Classifier: Programming Language :: Python :: 3.10
Classifier: Programming Language :: Python :: 3.11
Classifier: Programming Language :: Python :: 3.12
